brewinglib/db/__init__.py
brewinglib/db/base.py
brewinglib/db/columns.py
brewinglib/db/database.py
brewinglib/db/migrate.py
brewinglib/db/mixins.py
brewinglib/db/py.typed
brewinglib/db/settings.py
brewinglib/db/testing.py
brewinglib/db/types.py
brewinglib/db/_migrationcontext/README
brewinglib/db/_migrationcontext/__init__.py
brewinglib/db/_migrationcontext/env.py
brewinglib/db/_migrationcontext/script.py.mako
brewinglib_db-0.0.6.dist-info/METADATA
brewinglib_db-0.0.6.dist-info/WHEEL
brewinglib_db-0.0.6.dist-info/RECORD
